Workbook

Sheet Raw Sales Data
A1: Transaction ID | B1: Month | C1: Region | D1: Category | E1: Sales Rep | F1: Channel | G1: Units Sold | H1: Unit Price (AED) | I1: Revenue (AED) | J1: Cost (AED) | K1: Gross Profit (AED) | L1: Gross Margin % | M1: Target (AED) | N1: Achievement %
A2: TXN-2024-0001 | B2: Jan | C2: Dubai | D2: Electronics | E2: Omar Yousef | F2: Retail Store | G2: 124 | H2: 322.1 | I2: 39940.4 | J2: 18996.605 | K2: 20943.795 | L2: =K2/I2 -> 0.52437621 | M2: 44303.238 | N2: =I2/M2 -> 0.90152327
A3: TXN-2024-0002 | B3: Jan | C3: Jeddah | D3: Electronics | E3: Rami Nasser | F3: Online | G3: 25 | H3: 232.71 | I3: 5817.75 | J3: 2956.3782 | K3: 2861.3718 | L3: =K3/I3 -> 0.49183478 | M3: 6170.9256 | N3: =I3/M3 -> 0.94276781
A4: TXN-2024-0003 | B4: Jan | C4: Jeddah | D4: Furniture | E4: Rami Nasser | F4: Retail Store | G4: 239 | H4: 1199.07 | I4: 286577.73 | J4: 186951.16 | K4: 99626.566 | L4: =K4/I4 -> 0.34764239 | M4: 244242.91 | N4: =I4/M4 -> 1.1733308
A5: TXN-2024-0004 | B5: Jan | C5: Abu Dhabi | D5: Food & Beverage | E5: Layla Ibrahim | F5: Wholesale | G5: 89 | H5: 469.86 | I5: 41817.54 | J5: 26799.755 | K5: 15017.785 | L5: =K5/I5 -> 0.35912647 | M5: 37040.873 | N5: =I5/M5 -> 1.1289567
A6: TXN-2024-0005 | B6: Jan | C6: Riyadh | D6: Electronics | E6: Layla Ibrahim | F6: Wholesale | G6: 319 | H6: 565.82 | I6: 180496.58 | J6: 83184.125 | K6: 97312.455 | L6: =K6/I6 -> 0.53913739 | M6: 182445.71 | N6: =I6/M6 -> 0.98931666
A7: TXN-2024-0006 | B7: Jan | C7: Dubai | D7: Food & Beverage | E7: Sara Mohammed | F7: Wholesale | G7: 434 | H7: 1275.85 | I7: 553718.9 | J7: 371746.35 | K7: 181972.55 | L7: =K7/I7 -> 0.32863706 | M7: 540746.52 | N7: =I7/M7 -> 1.0239898
A8: TXN-2024-0007 | B8: Jan | C8: Abu Dhabi | D8: Electronics | E8: Ahmed Al-Rashid | F8: Retail Store | G8: 405 | H8: 614.31 | I8: 248795.55 | J8: 116920.97 | K8: 131874.58 | L8: =K8/I8 -> 0.53005201 | M8: 231747.29 | N8: =I8/M8 -> 1.073564
A9: TXN-2024-0008 | B9: Jan | C9: Dubai | D9: Food & Beverage | E9: Omar Yousef | F9: Direct Sales | G9: 335 | H9: 1676.52 | I9: 561634.2 | J9: 275573.42 | K9: 286060.78 | L9: =K9/I9 -> 0.50933648 | M9: 547225.33 | N9: =I9/M9 -> 1.0263308
A10: TXN-2024-0009 | B10: Jan | C10: Sharjah | D10: Electronics | E10: Khalid Hassan | F10: Retail Store | G10: 93 | H10: 951.41 | I10: 88481.13 | J10: 45787.831 | K10: 42693.299 | L10: =K10/I10 -> 0.48251304 | M10: 103866.84 | N10: =I10/M10 -> 0.85187081
A11: TXN-2024-0010 | B11: Jan | C11: Jeddah | D11: Furniture | E11: Layla Ibrahim | F11: Online | G11: 127 | H11: 1652.52 | I11: 209870.04 | J11: 136680.27 | K11: 73189.773 | L11: =K11/I11 -> 0.34873855 | M11: 207856.9 | N11: =I11/M11 -> 1.0096852
A12: TXN-2024-0011 | B12: Jan | C12: Dubai | D12: Furniture | E12: Layla Ibrahim | F12: Retail Store | G12: 345 | H12: 1023.5 | I12: 353107.5 | J12: 236995.44 | K12: 116112.06 | L12: =K12/I12 -> 0.32882921 | M12: 379589.91 | N12: =I12/M12 -> 0.93023416
A13: TXN-2024-0012 | B13: Jan | C13: Abu Dhabi | D13: Clothing | E13: Khalid Hassan | F13: Retail Store | G13: 391 | H13: 1144.67 | I13: 447565.97 | J13: 230803.24 | K13: 216762.73 | L13: =K13/I13 -> 0.4843146 | M13: 472005.35 | N13: =I13/M13 -> 0.94822223
... A241: TXN-2024-0240 | B241: Dec | C241: Sharjah | D241: Automotive | E241: Layla Ibrahim | F241: Direct Sales | G241: 372 | H241: 1147.7 | I241: 426944.4 | J241: 242813.16 | K241: 184131.24 | L241: =K241/I241 -> 0.43127685 | M241: 365388.81 | N241: =I241/M241 -> 1.168466

Sheet MIS Dashboard
A1: MONTHLY SALES MIS REPORT — FY 2024
A2: Company: Al-Rashid Trading LLC | Region: UAE & KSA | Currency: AED
A4: KEY PERFORMANCE INDICATORS
B5: KPI | D5: Value | F5: Target | H5: Variance | J5: Status
B6: Total Revenue (AED) | D6: =SUMIF('Raw Sales Data'!B:B,"Dec",'Raw Sales Data'!I:I) -> 5875993.1 | F6: 5,000,000 | H6: =D6-F6 -> 875993.11 | J6: =IF(H6>=0,"✅ On Track","⚠️ Below Target") -> ✅ On Track
B7: Total Units Sold | D7: =SUMIF('Raw Sales Data'!B:B,"Dec",'Raw Sales Data'!G:G) -> 4875 | F7: 50,000 | H7: =D7-F7 -> -45125 | J7: =IF(H7>=0,"✅ On Track","⚠️ Below Target") -> ⚠️ Below Target
B8: Avg Gross Margin % | D8: =AVERAGEIF('Raw Sales Data'!B:B,"Dec",'Raw Sales Data'!L:L) -> 0.43766667 | F8: 35% | H8: =D8-F8 -> 0.087666669 | J8: =IF(H8>=0,"✅ On Track","⚠️ Below Target") -> ✅ On Track
B9: No. of Transactions | D9: =COUNTIF('Raw Sales Data'!B:B,"Dec") -> 20 | F9: 20 | H9: =D9-F9 -> 0 | J9: =IF(H9>=0,"✅ On Track","⚠️ Below Target") -> ✅ On Track
A11: MONTHLY REVENUE TREND (AED)
A12: Month | B12: Revenue (AED) | C12: Cost (AED) | D12: Gross Profit (AED) | E12: Gross Margin % | F12: Units Sold | G12: Transactions | H12: Target (AED) | I12: Achievement %
A13: Jan | B13: =SUMIF('Raw Sales Data'!B:B,"Jan",'Raw Sales Data'!I:I) -> 5656673.8 | C13: =SUMIF('Raw Sales Data'!B:B,"Jan",'Raw Sales Data'!J:J) -> 3353010.8 | D13: =B13-C13 -> 2303663 | E13: =D13/B13 -> 0.40724692 | F13: =SUMIF('Raw Sales Data'!B:B,"Jan",'Raw Sales Data'!G:G) -> 5037 | G13: =COUNTIF('Raw Sales Data'!B:B,"Jan") -> 20 | H13: =SUMIF('Raw Sales Data'!B:B,"Jan",'Raw Sales Data'!M:M) -> 5908418.1 | I13: =B13/H13 -> 0.95739227
A14: Feb | B14: =SUMIF('Raw Sales Data'!B:B,"Feb",'Raw Sales Data'!I:I) -> 6357919.9 | C14: =SUMIF('Raw Sales Data'!B:B,"Feb",'Raw Sales Data'!J:J) -> 3785584.4 | D14: =B14-C14 -> 2572335.5 | E14: =D14/B14 -> 0.40458759 | F14: =SUMIF('Raw Sales Data'!B:B,"Feb",'Raw Sales Data'!G:G) -> 5391 | G14: =COUNTIF('Raw Sales Data'!B:B,"Feb") -> 20 | H14: =SUMIF('Raw Sales Data'!B:B,"Feb",'Raw Sales Data'!M:M) -> 6122858.3 | I14: =B14/H14 -> 1.0383908
A15: Mar | B15: =SUMIF('Raw Sales Data'!B:B,"Mar",'Raw Sales Data'!I:I) -> 4802104.7 | C15: =SUMIF('Raw Sales Data'!B:B,"Mar",'Raw Sales Data'!J:J) -> 2746509.9 | D15: =B15-C15 -> 2055594.8 | E15: =D15/B15 -> 0.42806122 | F15: =SUMIF('Raw Sales Data'!B:B,"Mar",'Raw Sales Data'!G:G) -> 5242 | G15: =COUNTIF('Raw Sales Data'!B:B,"Mar") -> 20 | H15: =SUMIF('Raw Sales Data'!B:B,"Mar",'Raw Sales Data'!M:M) -> 5128165.1 | I15: =B15/H15 -> 0.93641773
A16: Apr | B16: =SUMIF('Raw Sales Data'!B:B,"Apr",'Raw Sales Data'!I:I) -> 5735149.3 | C16: =SUMIF('Raw Sales Data'!B:B,"Apr",'Raw Sales Data'!J:J) -> 3295244.2 | D16: =B16-C16 -> 2439905.1 | E16: =D16/B16 -> 0.4254301 | F16: =SUMIF('Raw Sales Data'!B:B,"Apr",'Raw Sales Data'!G:G) -> 5016 | G16: =COUNTIF('Raw Sales Data'!B:B,"Apr") -> 20 | H16: =SUMIF('Raw Sales Data'!B:B,"Apr",'Raw Sales Data'!M:M) -> 5715908.9 | I16: =B16/H16 -> 1.0033661
A17: May | B17: =SUMIF('Raw Sales Data'!B:B,"May",'Raw Sales Data'!I:I) -> 4355945 | C17: =SUMIF('Raw Sales Data'!B:B,"May",'Raw Sales Data'!J:J) -> 2442282.1 | D17: =B17-C17 -> 1913662.8 | E17: =D17/B17 -> 0.43932209 | F17: =SUMIF('Raw Sales Data'!B:B,"May",'Raw Sales Data'!G:G) -> 5248 | G17: =COUNTIF('Raw Sales Data'!B:B,"May") -> 20 | H17: =SUMIF('Raw Sales Data'!B:B,"May",'Raw Sales Data'!M:M) -> 4514207.3 | I17: =B17/H17 -> 0.96494128
A18: Jun | B18: =SUMIF('Raw Sales Data'!B:B,"Jun",'Raw Sales Data'!I:I) -> 4820767.3 | C18: =SUMIF('Raw Sales Data'!B:B,"Jun",'Raw Sales Data'!J:J) -> 2720470.4 | D18: =B18-C18 -> 2100296.9 | E18: =D18/B18 -> 0.43567688 | F18: =SUMIF('Raw Sales Data'!B:B,"Jun",'Raw Sales Data'!G:G) -> 5437 | G18: =COUNTIF('Raw Sales Data'!B:B,"Jun") -> 20 | H18: =SUMIF('Raw Sales Data'!B:B,"Jun",'Raw Sales Data'!M:M) -> 5074422.2 | I18: =B18/H18 -> 0.95001306
A19: Jul | B19: =SUMIF('Raw Sales Data'!B:B,"Jul",'Raw Sales Data'!I:I) -> 5348235.2 | C19: =SUMIF('Raw Sales Data'!B:B,"Jul",'Raw Sales Data'!J:J) -> 3216673.3 | D19: =B19-C19 -> 2131561.8 | E19: =D19/B19 -> 0.39855424 | F19: =SUMIF('Raw Sales Data'!B:B,"Jul",'Raw Sales Data'!G:G) -> 5503 | G19: =COUNTIF('Raw Sales Data'!B:B,"Jul") -> 20 | H19: =SUMIF('Raw Sales Data'!B:B,"Jul",'Raw Sales Data'!M:M) -> 5388471.5 | I19: =B19/H19 -> 0.99253289
A20: Aug | B20: =SUMIF('Raw Sales Data'!B:B,"Aug",'Raw Sales Data'!I:I) -> 3972146.4 | C20: =SUMIF('Raw Sales Data'!B:B,"Aug",'Raw Sales Data'!J:J) -> 2358309.2 | D20: =B20-C20 -> 1613837.2 | E20: =D20/B20 -> 0.40628845 | F20: =SUMIF('Raw Sales Data'!B:B,"Aug",'Raw Sales Data'!G:G) -> 4616 | G20: =COUNTIF('Raw Sales Data'!B:B,"Aug") -> 20 | H20: =SUMIF('Raw Sales Data'!B:B,"Aug",'Raw Sales Data'!M:M) -> 4037942.3 | I20: =B20/H20 -> 0.98370559
A21: Sep | B21: =SUMIF('Raw Sales Data'!B:B,"Sep",'Raw Sales Data'!I:I) -> 4694757.8 | C21: =SUMIF('Raw Sales Data'!B:B,"Sep",'Raw Sales Data'!J:J) -> 2682850.8 | D21: =B21-C21 -> 2011907.1 | E21: =D21/B21 -> 0.42854331 | F21: =SUMIF('Raw Sales Data'!B:B,"Sep",'Raw Sales Data'!G:G) -> 4655 | G21: =COUNTIF('Raw Sales Data'!B:B,"Sep") -> 20 | H21: =SUMIF('Raw Sales Data'!B:B,"Sep",'Raw Sales Data'!M:M) -> 4775204.4 | I21: =B21/H21 -> 0.98315328
A22: Oct | B22: =SUMIF('Raw Sales Data'!B:B,"Oct",'Raw Sales Data'!I:I) -> 4307887.7 | C22: =SUMIF('Raw Sales Data'!B:B,"Oct",'Raw Sales Data'!J:J) -> 2476457.8 | D22: =B22-C22 -> 1831429.9 | E22: =D22/B22 -> 0.42513409 | F22: =SUMIF('Raw Sales Data'!B:B,"Oct",'Raw Sales Data'!G:G) -> 4541 | G22: =COUNTIF('Raw Sales Data'!B:B,"Oct") -> 20 | H22: =SUMIF('Raw Sales Data'!B:B,"Oct",'Raw Sales Data'!M:M) -> 4332824.4 | I22: =B22/H22 -> 0.99424471
A23: Nov | B23: =SUMIF('Raw Sales Data'!B:B,"Nov",'Raw Sales Data'!I:I) -> 5749972 | C23: =SUMIF('Raw Sales Data'!B:B,"Nov",'Raw Sales Data'!J:J) -> 3291793.9 | D23: =B23-C23 -> 2458178.1 | E23: =D23/B23 -> 0.42751132 | F23: =SUMIF('Raw Sales Data'!B:B,"Nov",'Raw Sales Data'!G:G) -> 5285 | G23: =COUNTIF('Raw Sales Data'!B:B,"Nov") -> 20 | H23: =SUMIF('Raw Sales Data'!B:B,"Nov",'Raw Sales Data'!M:M) -> 6071367.6 | I23: =B23/H23 -> 0.94706372
A24: Dec | B24: =SUMIF('Raw Sales Data'!B:B,"Dec",'Raw Sales Data'!I:I) -> 5875993.1 | C24: =SUMIF('Raw Sales Data'!B:B,"Dec",'Raw Sales Data'!J:J) -> 3267822.6 | D24: =B24-C24 -> 2608170.5 | E24: =D24/B24 -> 0.44386889 | F24: =SUMIF('Raw Sales Data'!B:B,"Dec",'Raw Sales Data'!G:G) -> 4875 | G24: =COUNTIF('Raw Sales Data'!B:B,"Dec") -> 20 | H24: =SUMIF('Raw Sales Data'!B:B,"Dec",'Raw Sales Data'!M:M) -> 6037323.7 | I24: =B24/H24 -> 0.97327779
A25: TOTAL / AVG | B25: =SUM(B13:B24) -> 61677552 | C25: =SUM(C13:C24) -> 35637010 | D25: =SUM(D13:D24) -> 26040543 | E25: =D25/B25 -> 0.42220454 | F25: =SUM(F13:F24) -> 60846 | G25: =SUM(G13:G24) -> 240 | H25: =SUM(H13:H24) -> 63107114 | I25: =B25/H25 -> 0.97734706
A27: REVENUE BY REGION (AED) | G27: REVENUE BY CATEGORY (AED)
A28: Region | B28: Revenue | C28: Units Sold | D28: Gross Profit | E28: Margin % | G28: Category | H28: Revenue | I28: Units | J28: Gross Profit | K28: Margin %
A29: Dubai | B29: =SUMIF('Raw Sales Data'!C:C,"Dubai",'Raw Sales Data'!I:I) -> 12276742 | C29: =SUMIF('Raw Sales Data'!C:C,"Dubai",'Raw Sales Data'!G:G) -> 11745 | D29: =SUMIF('Raw Sales Data'!C:C,"Dubai",'Raw Sales Data'!K:K) -> 5310077.7 | E29: =D29/B29 -> 0.43253151 | G29: Electronics | H29: =SUMIF('Raw Sales Data'!D:D,"Electronics",'Raw Sales Data'!I:I) -> 12545134 | I29: =SUMIF('Raw Sales Data'!D:D,"Electronics",'Raw Sales Data'!G:G) -> 12847 | J29: =SUMIF('Raw Sales Data'!D:D,"Electronics",'Raw Sales Data'!K:K) -> 5463156.5 | K29: =J29/H29 -> 0.43548012
A30: Abu Dhabi | B30: =SUMIF('Raw Sales Data'!C:C,"Abu Dhabi",'Raw Sales Data'!I:I) -> 10378322 | C30: =SUMIF('Raw Sales Data'!C:C,"Abu Dhabi",'Raw Sales Data'!G:G) -> 9954 | D30: =SUMIF('Raw Sales Data'!C:C,"Abu Dhabi",'Raw Sales Data'!K:K) -> 4328336.8 | E30: =D30/B30 -> 0.41705555 | G30: Furniture | H30: =SUMIF('Raw Sales Data'!D:D,"Furniture",'Raw Sales Data'!I:I) -> 12092698 | I30: =SUMIF('Raw Sales Data'!D:D,"Furniture",'Raw Sales Data'!G:G) -> 11391 | J30: =SUMIF('Raw Sales Data'!D:D,"Furniture",'Raw Sales Data'!K:K) -> 4980199.1 | K30: =J30/H30 -> 0.41183522
A31: Sharjah | B31: =SUMIF('Raw Sales Data'!C:C,"Sharjah",'Raw Sales Data'!I:I) -> 14085546 | C31: =SUMIF('Raw Sales Data'!C:C,"Sharjah",'Raw Sales Data'!G:G) -> 13414 | D31: =SUMIF('Raw Sales Data'!C:C,"Sharjah",'Raw Sales Data'!K:K) -> 5963930.6 | E31: =D31/B31 -> 0.42340783 | G31: Clothing | H31: =SUMIF('Raw Sales Data'!D:D,"Clothing",'Raw Sales Data'!I:I) -> 10485986 | I31: =SUMIF('Raw Sales Data'!D:D,"Clothing",'Raw Sales Data'!G:G) -> 9760 | J31: =SUMIF('Raw Sales Data'!D:D,"Clothing",'Raw Sales Data'!K:K) -> 4247988.4 | K31: =J31/H31 -> 0.40511103
A32: Riyadh | B32: =SUMIF('Raw Sales Data'!C:C,"Riyadh",'Raw Sales Data'!I:I) -> 14090261 | C32: =SUMIF('Raw Sales Data'!C:C,"Riyadh",'Raw Sales Data'!G:G) -> 14702 | D32: =SUMIF('Raw Sales Data'!C:C,"Riyadh",'Raw Sales Data'!K:K) -> 5886330.1 | E32: =D32/B32 -> 0.41775876 | G32: Food & Beverage | H32: =SUMIF('Raw Sales Data'!D:D,"Food & Beverage",'Raw Sales Data'!I:I) -> 13868858 | I32: =SUMIF('Raw Sales Data'!D:D,"Food & Beverage",'Raw Sales Data'!G:G) -> 14193 | J32: =SUMIF('Raw Sales Data'!D:D,"Food & Beverage",'Raw Sales Data'!K:K) -> 5968427.9 | K32: =J32/H32 -> 0.43034747
A33: Jeddah | B33: =SUMIF('Raw Sales Data'!C:C,"Jeddah",'Raw Sales Data'!I:I) -> 10846681 | C33: =SUMIF('Raw Sales Data'!C:C,"Jeddah",'Raw Sales Data'!G:G) -> 11031 | D33: =SUMIF('Raw Sales Data'!C:C,"Jeddah",'Raw Sales Data'!K:K) -> 4551867.5 | E33: =D33/B33 -> 0.41965534 | G33: Automotive | H33: =SUMIF('Raw Sales Data'!D:D,"Automotive",'Raw Sales Data'!I:I) -> 12684876 | I33: =SUMIF('Raw Sales Data'!D:D,"Automotive",'Raw Sales Data'!G:G) -> 12655 | J33: =SUMIF('Raw Sales Data'!D:D,"Automotive",'Raw Sales Data'!K:K) -> 5380770.8 | K33: =J33/H33 -> 0.42418788

Sheet Rep Performance
A1: SALES REP PERFORMANCE REPORT — FY 2024
A2: Sales Rep | B2: Total Revenue (AED) | C2: Units Sold | D2: Transactions | E2: Avg Deal Size (AED) | F2: Gross Profit (AED) | G2: Avg Margin % | H2: Performance
A3: Ahmed Al-Rashid | B3: =SUMIF('Raw Sales Data'!E:E,"Ahmed Al-Rashid",'Raw Sales Data'!I:I) -> 8825381.8 | C3: =SUMIF('Raw Sales Data'!E:E,"Ahmed Al-Rashid",'Raw Sales Data'!G:G) -> 8264 | D3: =COUNTIF('Raw Sales Data'!E:E,"Ahmed Al-Rashid") -> 29 | E3: =B3/D3 -> 304323.51 | F3: =SUMIF('Raw Sales Data'!E:E,"Ahmed Al-Rashid",'Raw Sales Data'!K:K) -> 3643609 | G3: =F3/B3 -> 0.41285568 | H3: =IF(G3>=0.35,"🏆 Top Performer",IF(G3>=0.3,"✅ On Track","⚠️ Needs Improvement")) -> 🏆 Top Performer
A4: Sara Mohammed | B4: =SUMIF('Raw Sales Data'!E:E,"Sara Mohammed",'Raw Sales Data'!I:I) -> 7622769.7 | C4: =SUMIF('Raw Sales Data'!E:E,"Sara Mohammed",'Raw Sales Data'!G:G) -> 7690 | D4: =COUNTIF('Raw Sales Data'!E:E,"Sara Mohammed") -> 33 | E4: =B4/D4 -> 230993.02 | F4: =SUMIF('Raw Sales Data'!E:E,"Sara Mohammed",'Raw Sales Data'!K:K) -> 3402040.9 | G4: =F4/B4 -> 0.44629984 | H4: =IF(G4>=0.35,"🏆 Top Performer",IF(G4>=0.3,"✅ On Track","⚠️ Needs Improvement")) -> 🏆 Top Performer
A5: Khalid Hassan | B5: =SUMIF('Raw Sales Data'!E:E,"Khalid Hassan",'Raw Sales Data'!I:I) -> 7664819.4 | C5: =SUMIF('Raw Sales Data'!E:E,"Khalid Hassan",'Raw Sales Data'!G:G) -> 7903 | D5: =COUNTIF('Raw Sales Data'!E:E,"Khalid Hassan") -> 32 | E5: =B5/D5 -> 239525.61 | F5: =SUMIF('Raw Sales Data'!E:E,"Khalid Hassan",'Raw Sales Data'!K:K) -> 3081849.6 | G5: =F5/B5 -> 0.40207726 | H5: =IF(G5>=0.35,"🏆 Top Performer",IF(G5>=0.3,"✅ On Track","⚠️ Needs Improvement")) -> 🏆 Top Performer
A6: Fatima Al-Ali | B6: =SUMIF('Raw Sales Data'!E:E,"Fatima Al-Ali",'Raw Sales Data'!I:I) -> 5496842.7 | C6: =SUMIF('Raw Sales Data'!E:E,"Fatima Al-Ali",'Raw Sales Data'!G:G) -> 7188 | D6: =COUNTIF('Raw Sales Data'!E:E,"Fatima Al-Ali") -> 30 | E6: =B6/D6 -> 183228.09 | F6: =SUMIF('Raw Sales Data'!E:E,"Fatima Al-Ali",'Raw Sales Data'!K:K) -> 2318419.6 | G6: =F6/B6 -> 0.42177296 | H6: =IF(G6>=0.35,"🏆 Top Performer",IF(G6>=0.3,"✅ On Track","⚠️ Needs Improvement")) -> 🏆 Top Performer
A7: Omar Yousef | B7: =SUMIF('Raw Sales Data'!E:E,"Omar Yousef",'Raw Sales Data'!I:I) -> 6044130.7 | C7: =SUMIF('Raw Sales Data'!E:E,"Omar Yousef",'Raw Sales Data'!G:G) -> 6055 | D7: =COUNTIF('Raw Sales Data'!E:E,"Omar Yousef") -> 26 | E7: =B7/D7 -> 232466.56 | F7: =SUMIF('Raw Sales Data'!E:E,"Omar Yousef",'Raw Sales Data'!K:K) -> 2498974.3 | G7: =F7/B7 -> 0.41345471 | H7: =IF(G7>=0.35,"🏆 Top Performer",IF(G7>=0.3,"✅ On Track","⚠️ Needs Improvement")) -> 🏆 Top Performer
A8: Layla Ibrahim | B8: =SUMIF('Raw Sales Data'!E:E,"Layla Ibrahim",'Raw Sales Data'!I:I) -> 10071956 | C8: =SUMIF('Raw Sales Data'!E:E,"Layla Ibrahim",'Raw Sales Data'!G:G) -> 9159 | D8: =COUNTIF('Raw Sales Data'!E:E,"Layla Ibrahim") -> 35 | E8: =B8/D8 -> 287770.17 | F8: =SUMIF('Raw Sales Data'!E:E,"Layla Ibrahim",'Raw Sales Data'!K:K) -> 4058461.9 | G8: =F8/B8 -> 0.40294675 | H8: =IF(G8>=0.35,"🏆 Top Performer",IF(G8>=0.3,"✅ On Track","⚠️ Needs Improvement")) -> 🏆 Top Performer
A9: Rami Nasser | B9: =SUMIF('Raw Sales Data'!E:E,"Rami Nasser",'Raw Sales Data'!I:I) -> 6392810.2 | C9: =SUMIF('Raw Sales Data'!E:E,"Rami Nasser",'Raw Sales Data'!G:G) -> 4946 | D9: =COUNTIF('Raw Sales Data'!E:E,"Rami Nasser") -> 22 | E9: =B9/D9 -> 290582.28 | F9: =SUMIF('Raw Sales Data'!E:E,"Rami Nasser",'Raw Sales Data'!K:K) -> 2893090.6 | G9: =F9/B9 -> 0.45255381 | H9: =IF(G9>=0.35,"🏆 Top Performer",IF(G9>=0.3,"✅ On Track","⚠️ Needs Improvement")) -> 🏆 Top Performer
A10: Hana Saeed | B10: =SUMIF('Raw Sales Data'!E:E,"Hana Saeed",'Raw Sales Data'!I:I) -> 9558842.1 | C10: =SUMIF('Raw Sales Data'!E:E,"Hana Saeed",'Raw Sales Data'!G:G) -> 9641 | D10: =COUNTIF('Raw Sales Data'!E:E,"Hana Saeed") -> 33 | E10: =B10/D10 -> 289661.88 | F10: =SUMIF('Raw Sales Data'!E:E,"Hana Saeed",'Raw Sales Data'!K:K) -> 4144096.9 | G10: =F10/B10 -> 0.43353545 | H10: =IF(G10>=0.35,"🏆 Top Performer",IF(G10>=0.3,"✅ On Track","⚠️ Needs Improvement")) -> 🏆 Top Performer
